pcs_argpass/LogP.py
pcs_argpass/Param.py
pcs_argpass/__init__.py
pcs_argpass/pcs_argpass/Param.py
pcs_argpass/pcs_argpass/__init__.py
pcs_log/LogP.py
pcs_log/PortLogServer.py
pcs_log/__init__.py
pcs_argpass-0.9.4.dist-info/LICENSE
pcs_argpass-0.9.4.dist-info/METADATA
pcs_argpass-0.9.4.dist-info/WHEEL
pcs_argpass-0.9.4.dist-info/top_level.txt
pcs_argpass-0.9.4.dist-info/RECORD
