Metadata-Version: 2.1
Name: pcs-argpass
Version: 0.9.4
Summary: Argument parser and checker.
Home-page: https://github.com/rpietsch1953/pcs-pylibs
Author: Rainer Pietsch
Author-email: r.pietsch@pcs-at.com
Classifier: Programming Language :: Python :: 3
Classifier: License :: OSI Approved :: GNU General Public License v2 (GPLv2)
Classifier: Operating System :: OS Independent
Requires-Python: >=3.6
License-File: LICENSE
